{
  "id": "room_ynqlo6",
  "name": "Neon Highway 26,10",
  "description": "A placeholder location waiting for development.",
  "type": "street",
  "coordinates": {
    "x": 26,
    "y": 10,
    "z": 0
  },
  "exits": {},
  "features": [],
  "spawns": [],
  "_metadata": {
    "proposalId": "b3c46dc3-e797-4238-8091-5092dbdc8fc5",
    "generatedAt": 1768368508277,
    "publishedAt": 1768368508277,
    "seed": "oia89e",
    "flavor": {
      "rationale": "Expanding the world with a new indoor block."
    }
  }
}